{"ZTF20aajcdad": {"name": "ZTF20aajcdad", "sources": [{"name": "gp3", "alias": "1"}], "alias": [{"value": "ZTF20aajcdad", "source": "1"}], "photometry": [{"time": 58875.394490700215, "band": "i", "instrument": "P48", "telescope": "P48", "magnitude": 19.243042786811408, "e_magnitude": 0.06407750294359413, "u_time": "MJD", "source": "1", "system": "AB"}, {"time": 58875.41305560013, "band": "i", "instrument": "P48", "telescope": "P48", "magnitude": 19.289007080569373, "e_magnitude": 0.0749998738805582, "u_time": "MJD", "source": "1", "system": "AB"}, {"time": 58875.47399309976, "band": "g", "instrument": "P48", "telescope": "P48", "magnitude": 19.190743148084778, "e_magnitude": 0.04962089980479071, "u_time": "MJD", "source": "1", "system": "AB"}, {"time": 58875.47491899971, "band": "g", "instrument": "P48", "telescope": "P48", "magnitude": 19.16075854677993, "e_magnitude": 0.04839432140521752, "u_time": "MJD", "source": "1", "system": "AB"}, {"time": 58875.496388900094, "band": "g", "instrument": "P48", "telescope": "P48", "magnitude": 19.121082670739646, "e_magnitude": 0.04327582540177531, "u_time": "MJD", "source": "1", "system": "AB"}, {"time": 58875.505358799826, "band": "r", "instrument": "P48", "telescope": "P48", "magnitude": 18.90674827197637, "e_magnitude": 0.04562997327597559, "u_time": "MJD", "source": "1", "system": "AB"}, {"time": 58875.52670140006, "band": "r", "instrument": "P48", "telescope": "P48", "magnitude": 18.876599796131188, "e_magnitude": 0.03960421171079224, "u_time": "MJD", "source": "1", "system": "AB"}, {"time": 58875.52761569992, "band": "r", "instrument": "P48", "telescope": "P48", "magnitude": 18.924263931937965, "e_magnitude": 0.04208959862212356, "u_time": "MJD", "source": "1", "system": "AB"}, {"time": 58876.46615739958, "band": "i", "instrument": "P48", "telescope": "P48", "magnitude": 18.77424419152267, "e_magnitude": 0.02921323082122819, "u_time": "MJD", "source": "1", "system": "AB"}, {"time": 58876.501099499874, "band": "i", "instrument": "P48", "telescope": "P48", "magnitude": 18.782321597690963, "e_magnitude": 0.03004270522123841, "u_time": "MJD", "source": "1", "system": "AB"}, {"time": 58876.52369210031, "band": "g", "instrument": "P48", "telescope": "P48", "magnitude": 18.802266019508636, "e_magnitude": 0.02892295813844829, "u_time": "MJD", "source": "1", "system": "AB"}, {"time": 58876.546180599835, "band": "r", "instrument": "P48", "telescope": "P48", "magnitude": 18.622277119599854, "e_magnitude": 0.028589032952754962, "u_time": "MJD", "source": "1", "system": "AB"}, {"time": 58876.565624999814, "band": "r", "instrument": "P48", "telescope": "P48", "magnitude": 18.594590146117277, "e_magnitude": 0.02720465372080937, "u_time": "MJD", "source": "1", "system": "AB"}, {"time": 58877.44350690022, "band": "i", "instrument": "P48", "telescope": "P48", "magnitude": 18.606448544274603, "e_magnitude": 0.03181155751308805, "u_time": "MJD", "source": "1", "system": "AB"}, {"time": 58877.46325229993, "band": "i", "instrument": "P48", "telescope": "P48", "magnitude": 18.582787260420385, "e_magnitude": 0.03546749613659193, "u_time": "MJD", "source": "1", "system": "AB"}, {"time": 58877.49887729995, "band": "r", "instrument": "P48", "telescope": "P48", "magnitude": 18.40845036817617, "e_magnitude": 0.02737372935558116, "u_time": "MJD", "source": "1", "system": "AB"}, {"time": 58877.50373840006, "band": "r", "instrument": "P48", "telescope": "P48", "magnitude": 18.38352863489734, "e_magnitude": 0.02350128957831919, "u_time": "MJD", "source": "1", "system": "AB"}, {"time": 58877.545578700025, "band": "g", "instrument": "P48", "telescope": "P48", "magnitude": 18.675374424451835, "e_magnitude": 0.03255974275881344, "u_time": "MJD", "source": "1", "system": "AB"}, {"time": 58878.4447337999, "band": "i", "instrument": "P48", "telescope": "P48", "magnitude": 18.321964266141844, "e_magnitude": 0.02928868474427611, "u_time": "MJD", "source": "1", "system": "AB"}, {"time": 58878.46577550005, "band": "i", "instrument": "P48", "telescope": "P48", "magnitude": 18.36035962739517, "e_magnitude": 0.031235078186491447, "u_time": "MJD", "source": "1", "system": "AB"}, {"time": 58878.50502310041, "band": "g", "instrument": "P48", "telescope": "P48", "magnitude": 18.44499502629843, "e_magnitude": 0.029322806498390263, "u_time": "MJD", "source": "1", "system": "AB"}, {"time": 58878.54576390004, "band": "r", "instrument": "P48", "telescope": "P48", "magnitude": 18.16091521996158, "e_magnitude": 0.032135382106565816, "u_time": "MJD", "source": "1", "system": "AB"}, {"time": 58878.54668979999, "band": "r", "instrument": "P48", "telescope": "P48", "magnitude": 18.21362971669199, "e_magnitude": 0.03228302816869884, "u_time": "MJD", "source": "1", "system": "AB"}, {"time": 58878.56576390006, "band": "r", "instrument": "P48", "telescope": "P48", "magnitude": 18.18979976711382, "e_magnitude": 0.030588265034095865, "u_time": "MJD", "source": "1", "system": "AB"}, {"time": 58879.41642360017, "band": "i", "instrument": "P48", "telescope": "P48", "magnitude": 18.047093173922928, "e_magnitude": 0.028910443603376686, "u_time": "MJD", "source": "1", "system": "AB"}, {"time": 58879.444108799566, "band": "i", "instrument": "P48", "telescope": "P48", "magnitude": 18.147843767209324, "e_magnitude": 0.035272745371085254, "u_time": "MJD", "source": "1", "system": "AB"}, {"time": 58879.47883100016, "band": "g", "instrument": "P48", "telescope": "P48", "magnitude": 18.01527094967017, "e_magnitude": 0.025566710885637955, "u_time": "MJD", "source": "1", "system": "AB"}, {"time": 58879.485161999706, "band": "g", "instrument": "P48", "telescope": "P48", "magnitude": 18.08744811349343, "e_magnitude": 0.02124772906094648, "u_time": "MJD", "source": "1", "system": "AB"}, {"time": 58879.52854170045, "band": "r", "instrument": "P48", "telescope": "P48", "magnitude": 18.015264237101313, "e_magnitude": 0.039548975917370076, "u_time": "MJD", "source": "1", "system": "AB"}, {"time": 58879.55494210031, "band": "r", "instrument": "P48", "telescope": "P48", "magnitude": 18.073949300165218, "e_magnitude": 0.04109788302496946, "u_time": "MJD", "source": "1", "system": "AB"}, {"time": 58880.404652799945, "band": "i", "instrument": "P48", "telescope": "P48", "magnitude": 17.91254123271937, "e_magnitude": 0.01829512306213921, "u_time": "MJD", "source": "1", "system": "AB"}, {"time": 58880.47928239964, "band": "g", "instrument": "P48", "telescope": "P48", "magnitude": 17.800229172426615, "e_magnitude": 0.016241046838783905, "u_time": "MJD", "source": "1", "system": "AB"}, {"time": 58880.49857639987, "band": "g", "instrument": "P48", "telescope": "P48", "magnitude": 17.78727717480033, "e_magnitude": 0.015596691262675707, "u_time": "MJD", "source": "1", "system": "AB"}, {"time": 58880.50364579959, "band": "r", "instrument": "P48", "telescope": "P48", "magnitude": 17.68639548555288, "e_magnitude": 0.016152691712634542, "u_time": "MJD", "source": "1", "system": "AB"}, {"time": 58880.52527779993, "band": "r", "instrument": "P48", "telescope": "P48", "magnitude": 17.6669980182961, "e_magnitude": 0.015993210917370562, "u_time": "MJD", "source": "1", "system": "AB"}, {"time": 58880.547893499956, "band": "i", "instrument": "P48", "telescope": "P48", "magnitude": 17.8676448113314, "e_magnitude": 0.01595100115972293, "u_time": "MJD", "source": "1", "system": "AB"}, {"time": 58881.46556710033, "band": "g", "instrument": "P48", "telescope": "P48", "magnitude": 17.525311081239806, "e_magnitude": 0.01271805841815459, "u_time": "MJD", "source": "1", "system": "AB"}, {"time": 58881.495405100286, "band": "g", "instrument": "P48", "telescope": "P48", "magnitude": 17.50685651425827, "e_magnitude": 0.012770414259913706, "u_time": "MJD", "source": "1", "system": "AB"}, {"time": 58881.49631940015, "band": "g", "instrument": "P48", "telescope": "P48", "magnitude": 17.534494644607072, "e_magnitude": 0.013635674766858528, "u_time": "MJD", "source": "1", "system": "AB"}, {"time": 58881.535393500235, "band": "r", "instrument": "P48", "telescope": "P48", "magnitude": 17.473732688327903, "e_magnitude": 0.014147759450578988, "u_time": "MJD", "source": "1", "system": "AB"}, {"time": 58881.536319400184, "band": "r", "instrument": "P48", "telescope": "P48", "magnitude": 17.5000530306537, "e_magnitude": 0.014298130838601548, "u_time": "MJD", "source": "1", "system": "AB"}, {"time": 58881.56291670026, "band": "r", "instrument": "P48", "telescope": "P48", "magnitude": 17.492841229135006, "e_magnitude": 0.013920791708636382, "u_time": "MJD", "source": "1", "system": "AB"}, {"time": 58881.567013899796, "band": "i", "instrument": "P48", "telescope": "P48", "magnitude": 17.6843154224562, "e_magnitude": 0.014327119365612156, "u_time": "MJD", "source": "1", "system": "AB"}, {"time": 58883.337187500205, "band": "i", "instrument": "P48", "telescope": "P48", "magnitude": 17.499174644416325, "e_magnitude": 0.02338726417587859, "u_time": "MJD", "source": "1", "system": "AB"}, {"time": 58883.39363429975, "band": "i", "instrument": "P48", "telescope": "P48", "magnitude": 17.484245201745207, "e_magnitude": 0.017289501321005814, "u_time": "MJD", "source": "1", "system": "AB"}, {"time": 58883.47722220002, "band": "g", "instrument": "P48", "telescope": "P48", "magnitude": 17.36296333528383, "e_magnitude": 0.014315360362483327, "u_time": "MJD", "source": "1", "system": "AB"}, {"time": 58883.49759260006, "band": "g", "instrument": "P48", "telescope": "P48", "magnitude": 17.368755370711664, "e_magnitude": 0.014562741949156889, "u_time": "MJD", "source": "1", "system": "AB"}, {"time": 58883.53570599994, "band": "r", "instrument": "P48", "telescope": "P48", "magnitude": 17.324139817840653, "e_magnitude": 0.016733341519125762, "u_time": "MJD", "source": "1", "system": "AB"}, {"time": 58883.542789399624, "band": "r", "instrument": "P48", "telescope": "P48", "magnitude": 17.312984075711363, "e_magnitude": 0.015397496680237927, "u_time": "MJD", "source": "1", "system": "AB"}, {"time": 58884.39353010012, "band": "i", "instrument": "P48", "telescope": "P48", "magnitude": 17.417653324353267, "e_magnitude": 0.015536703552911903, "u_time": "MJD", "source": "1", "system": "AB"}, {"time": 58884.4144444, "band": "i", "instrument": "P48", "telescope": "P48", "magnitude": 17.365576493833203, "e_magnitude": 0.013983936861791904, "u_time": "MJD", "source": "1", "system": "AB"}, {"time": 58884.436307899654, "band": "g", "instrument": "P48", "telescope": "P48", "magnitude": 17.241957751906654, "e_magnitude": 0.013573169419505203, "u_time": "MJD", "source": "1", "system": "AB"}, {"time": 58884.445092600305, "band": "g", "instrument": "P48", "telescope": "P48", "magnitude": 17.254402523094644, "e_magnitude": 0.014057676672394803, "u_time": "MJD", "source": "1", "system": "AB"}, {"time": 58884.47677079961, "band": "g", "instrument": "P48", "telescope": "P48", "magnitude": 17.279323039437777, "e_magnitude": 0.013354182452573814, "u_time": "MJD", "source": "1", "system": "AB"}, {"time": 58884.503124999814, "band": "r", "instrument": "P48", "telescope": "P48", "magnitude": 17.299328709498653, "e_magnitude": 0.020306316184158915, "u_time": "MJD", "source": "1", "system": "AB"}, {"time": 58884.53020829987, "band": "r", "instrument": "P48", "telescope": "P48", "magnitude": 17.22369895839769, "e_magnitude": 0.013686711288715799, "u_time": "MJD", "source": "1", "system": "AB"}, {"time": 58885.37381940009, "band": "i", "instrument": "P48", "telescope": "P48", "magnitude": 17.348454595685965, "e_magnitude": 0.01704466851155234, "u_time": "MJD", "source": "1", "system": "AB"}, {"time": 58885.41575230006, "band": "i", "instrument": "P48", "telescope": "P48", "magnitude": 17.31553334261759, "e_magnitude": 0.016698024840695304, "u_time": "MJD", "source": "1", "system": "AB"}, {"time": 58885.428541700356, "band": "g", "instrument": "P48", "telescope": "P48", "magnitude": 17.19242912578465, "e_magnitude": 0.015502047319414231, "u_time": "MJD", "source": "1", "system": "AB"}, {"time": 58885.45802079979, "band": "g", "instrument": "P48", "telescope": "P48", "magnitude": 17.149314205116823, "e_magnitude": 0.014384653746461848, "u_time": "MJD", "source": "1", "system": "AB"}, {"time": 58885.53063660022, "band": "r", "instrument": "P48", "telescope": "P48", "magnitude": 17.1385621050851, "e_magnitude": 0.012217173196130934, "u_time": "MJD", "source": "1", "system": "AB"}, {"time": 58886.393854200374, "band": "i", "instrument": "P48", "telescope": "P48", "magnitude": 17.189913308508316, "e_magnitude": 0.011995544847793728, "u_time": "MJD", "source": "1", "system": "AB"}, {"time": 58886.41473379964, "band": "i", "instrument": "P48", "telescope": "P48", "magnitude": 17.176677568274137, "e_magnitude": 0.011197738844748978, "u_time": "MJD", "source": "1", "system": "AB"}, {"time": 58886.47774309991, "band": "g", "instrument": "P48", "telescope": "P48", "magnitude": 17.0408943847659, "e_magnitude": 0.012700610823304424, "u_time": "MJD", "source": "1", "system": "AB"}, {"time": 58886.49319439987, "band": "g", "instrument": "P48", "telescope": "P48", "magnitude": 17.01649391553061, "e_magnitude": 0.012028207516831563, "u_time": "MJD", "source": "1", "system": "AB"}, {"time": 58886.53354170034, "band": "r", "instrument": "P48", "telescope": "P48", "magnitude": 17.049645354813947, "e_magnitude": 0.012411245209775618, "u_time": "MJD", "source": "1", "system": "AB"}, {"time": 58886.54906249978, "band": "r", "instrument": "P48", "telescope": "P48", "magnitude": 17.07198176567354, "e_magnitude": 0.012939838218650634, "u_time": "MJD", "source": "1", "system": "AB"}, {"time": 58887.42853010027, "band": "g", "instrument": "P48", "telescope": "P48", "magnitude": 17.114832032806667, "e_magnitude": 0.017342210475812223, "u_time": "MJD", "source": "1", "system": "AB"}, {"time": 58887.44673610013, "band": "g", "instrument": "P48", "telescope": "P48", "magnitude": 17.059960451697524, "e_magnitude": 0.016402449936658747, "u_time": "MJD", "source": "1", "system": "AB"}, {"time": 58887.47651620023, "band": "g", "instrument": "P48", "telescope": "P48", "magnitude": 17.08812274113167, "e_magnitude": 0.015565082991824936, "u_time": "MJD", "source": "1", "system": "AB"}, {"time": 58887.49781250022, "band": "r", "instrument": "P48", "telescope": "P48", "magnitude": 17.052623523039607, "e_magnitude": 0.01346206828004634, "u_time": "MJD", "source": "1", "system": "AB"}, {"time": 58887.5135764, "band": "r", "instrument": "P48", "telescope": "P48", "magnitude": 17.040219745693797, "e_magnitude": 0.014138502863989096, "u_time": "MJD", "source": "1", "system": "AB"}, {"time": 58887.523321799934, "band": "r", "instrument": "P48", "telescope": "P48", "magnitude": 17.03098517940459, "e_magnitude": 0.013454827476215549, "u_time": "MJD", "source": "1", "system": "AB"}, {"time": 58888.395115700085, "band": "i", "instrument": "P48", "telescope": "P48", "magnitude": 17.205752963016163, "e_magnitude": 0.01761924492009471, "u_time": "MJD", "source": "1", "system": "AB"}, {"time": 58888.41266199993, "band": "i", "instrument": "P48", "telescope": "P48", "magnitude": 17.204530164030306, "e_magnitude": 0.02056064798185341, "u_time": "MJD", "source": "1", "system": "AB"}, {"time": 58888.475613399874, "band": "r", "instrument": "P48", "telescope": "P48", "magnitude": 17.117339226023336, "e_magnitude": 0.020604200154165288, "u_time": "MJD", "source": "1", "system": "AB"}, {"time": 58888.488286999986, "band": "r", "instrument": "P48", "telescope": "P48", "magnitude": 17.08039515948039, "e_magnitude": 0.0206141238599601, "u_time": "MJD", "source": "1", "system": "AB"}, {"time": 58888.53140050033, "band": "g", "instrument": "P48", "telescope": "P48", "magnitude": 17.246259122209068, "e_magnitude": 0.03827064601586899, "u_time": "MJD", "source": "1", "system": "AB"}, {"time": 58890.31581020029, "band": "i", "instrument": "P48", "telescope": "P48", "magnitude": 17.21122116479524, "e_magnitude": 0.025129269647108606, "u_time": "MJD", "source": "1", "system": "AB"}, {"time": 58890.37767359987, "band": "i", "instrument": "P48", "telescope": "P48", "magnitude": 17.19045827557573, "e_magnitude": 0.016652999959539082, "u_time": "MJD", "source": "1", "system": "AB"}, {"time": 58890.45748839993, "band": "r", "instrument": "P48", "telescope": "P48", "magnitude": 17.159142207977233, "e_magnitude": 0.023455355134100006, "u_time": "MJD", "source": "1", "system": "AB"}, {"time": 58890.46057870006, "band": "r", "instrument": "P48", "telescope": "P48", "magnitude": 17.2219383987534, "e_magnitude": 0.028975529217165022, "u_time": "MJD", "source": "1", "system": "AB"}, {"time": 58890.47659720015, "band": "r", "instrument": "P48", "telescope": "P48", "magnitude": 17.22930083743709, "e_magnitude": 0.025380631440019882, "u_time": "MJD", "source": "1", "system": "AB"}, {"time": 58890.540092600044, "band": "g", "instrument": "P48", "telescope": "P48", "magnitude": 17.447310126895168, "e_magnitude": 0.036936580443788544, "u_time": "MJD", "source": "1", "system": "AB"}, {"time": 58890.54101849999, "band": "g", "instrument": "P48", "telescope": "P48", "magnitude": 17.506912554073647, "e_magnitude": 0.03485757527035693, "u_time": "MJD", "source": "1", "system": "AB"}, {"time": 58890.56074069999, "band": "g", "instrument": "P48", "telescope": "P48", "magnitude": 17.525833912603428, "e_magnitude": 0.04364953032370154, "u_time": "MJD", "source": "1", "system": "AB"}, {"time": 58891.39839120023, "band": "i", "instrument": "P48", "telescope": "P48", "magnitude": 17.213106908841464, "e_magnitude": 0.015384190164175878, "u_time": "MJD", "source": "1", "system": "AB"}, {"time": 58891.45615739981, "band": "g", "instrument": "P48", "telescope": "P48", "magnitude": 17.371310015359775, "e_magnitude": 0.019178294183987823, "u_time": "MJD", "source": "1", "system": "AB"}, {"time": 58891.46170140011, "band": "g", "instrument": "P48", "telescope": "P48", "magnitude": 17.41468019323193, "e_magnitude": 0.01975442504877302, "u_time": "MJD", "source": "1", "system": "AB"}, {"time": 58891.48099539988, "band": "r", "instrument": "P48", "telescope": "P48", "magnitude": 17.221191015945948, "e_magnitude": 0.019386951353175676, "u_time": "MJD", "source": "1", "system": "AB"}, {"time": 58891.50519679999, "band": "r", "instrument": "P48", "telescope": "P48", "magnitude": 17.049376787987626, "e_magnitude": 0.013321557594191147, "u_time": "MJD", "source": "1", "system": "AB"}, {"time": 58892.319166700356, "band": "r", "instrument": "P48", "telescope": "P48", "magnitude": 17.19247778062865, "e_magnitude": 0.017842314567314558, "u_time": "MJD", "source": "1", "system": "AB"}, {"time": 58892.35967590008, "band": "g", "instrument": "P48", "telescope": "P48", "magnitude": 17.513343405977484, "e_magnitude": 0.022919098003231404, "u_time": "MJD", "source": "1", "system": "AB"}, {"time": 58892.39401620021, "band": "g", "instrument": "P48", "telescope": "P48", "magnitude": 17.46669906115539, "e_magnitude": 0.018339215432544485, "u_time": "MJD", "source": "1", "system": "AB"}, {"time": 58892.43768520001, "band": "i", "instrument": "P48", "telescope": "P48", "magnitude": 17.146136796135405, "e_magnitude": 0.009988447780783893, "u_time": "MJD", "source": "1", "system": "AB"}, {"time": 58892.45820600027, "band": "i", "instrument": "P48", "telescope": "P48", "magnitude": 17.173143045888565, "e_magnitude": 0.01077107011511116, "u_time": "MJD", "source": "1", "system": "AB"}, {"time": 58892.50549770007, "band": "r", "instrument": "P48", "telescope": "P48", "magnitude": 17.168028934856967, "e_magnitude": 0.0138907681196932, "u_time": "MJD", "source": "1", "system": "AB"}, {"time": 58893.40011569997, "band": "i", "instrument": "P48", "telescope": "P48", "magnitude": 17.178327762767093, "e_magnitude": 0.010697774463160729, "u_time": "MJD", "source": "1", "system": "AB"}, {"time": 58893.43478010036, "band": "i", "instrument": "P48", "telescope": "P48", "magnitude": 17.23120451162818, "e_magnitude": 0.011929906891435235, "u_time": "MJD", "source": "1", "system": "AB"}, {"time": 58893.45599539997, "band": "g", "instrument": "P48", "telescope": "P48", "magnitude": 17.547427492767476, "e_magnitude": 0.016253101161553714, "u_time": "MJD", "source": "1", "system": "AB"}, {"time": 58893.45690969983, "band": "g", "instrument": "P48", "telescope": "P48", "magnitude": 17.580343255756027, "e_magnitude": 0.016277964739739616, "u_time": "MJD", "source": "1", "system": "AB"}, {"time": 58893.47745370027, "band": "g", "instrument": "P48", "telescope": "P48", "magnitude": 17.59526495818876, "e_magnitude": 0.016667569722307315, "u_time": "MJD", "source": "1", "system": "AB"}, {"time": 58893.505891200155, "band": "r", "instrument": "P48", "telescope": "P48", "magnitude": 17.208132366513276, "e_magnitude": 0.01388929052022082, "u_time": "MJD", "source": "1", "system": "AB"}, {"time": 58893.50680560013, "band": "r", "instrument": "P48", "telescope": "P48", "magnitude": 17.18619004896074, "e_magnitude": 0.013175566806506025, "u_time": "MJD", "source": "1", "system": "AB"}, {"time": 58893.54170140019, "band": "r", "instrument": "P48", "telescope": "P48", "magnitude": 17.20935191247417, "e_magnitude": 0.0127893194526626, "u_time": "MJD", "source": "1", "system": "AB"}, {"time": 58894.338391200174, "band": "g", "instrument": "P48", "telescope": "P48", "magnitude": 17.765735200717508, "e_magnitude": 0.018131129409232814, "u_time": "MJD", "source": "1", "system": "AB"}, {"time": 58894.369004600216, "band": "g", "instrument": "P48", "telescope": "P48", "magnitude": 17.723200910280006, "e_magnitude": 0.017463354313245378, "u_time": "MJD", "source": "1", "system": "AB"}, {"time": 58894.406365700066, "band": "i", "instrument": "P48", "telescope": "P48", "magnitude": 17.292560272002277, "e_magnitude": 0.010333256479108077, "u_time": "MJD", "source": "1", "system": "AB"}, {"time": 58894.4375, "band": "i", "instrument": "P48", "telescope": "P48", "magnitude": 17.27781536938618, "e_magnitude": 0.009884110979031965, "u_time": "MJD", "source": "1", "system": "AB"}, {"time": 58894.47957179975, "band": "r", "instrument": "P48", "telescope": "P48", "magnitude": 17.277596122536114, "e_magnitude": 0.012827307071581943, "u_time": "MJD", "source": "1", "system": "AB"}, {"time": 58894.504201400094, "band": "r", "instrument": "P48", "telescope": "P48", "magnitude": 17.304623657045468, "e_magnitude": 0.01311514963639458, "u_time": "MJD", "source": "1", "system": "AB"}, {"time": 58895.35165510047, "band": "i", "instrument": "P48", "telescope": "P48", "magnitude": 17.32245258443313, "e_magnitude": 0.011113681759814755, "u_time": "MJD", "source": "1", "system": "AB"}, {"time": 58895.37493060017, "band": "i", "instrument": "P48", "telescope": "P48", "magnitude": 17.349612856162857, "e_magnitude": 0.01173837250444402, "u_time": "MJD", "source": "1", "system": "AB"}, {"time": 58895.38681709999, "band": "g", "instrument": "P48", "telescope": "P48", "magnitude": 17.924394174440124, "e_magnitude": 0.01801887855600018, "u_time": "MJD", "source": "1", "system": "AB"}, {"time": 58895.41137730004, "band": "g", "instrument": "P48", "telescope": "P48", "magnitude": 17.96701755397219, "e_magnitude": 0.020001790797089875, "u_time": "MJD", "source": "1", "system": "AB"}, {"time": 58895.456851899624, "band": "r", "instrument": "P48", "telescope": "P48", "magnitude": 17.358908195982043, "e_magnitude": 0.013565146971183165, "u_time": "MJD", "source": "1", "system": "AB"}, {"time": 58895.46664350014, "band": "r", "instrument": "P48", "telescope": "P48", "magnitude": 17.36819615487449, "e_magnitude": 0.013143262173808238, "u_time": "MJD", "source": "1", "system": "AB"}, {"time": 58896.35164349992, "band": "i", "instrument": "P48", "telescope": "P48", "magnitude": 17.384056215796114, "e_magnitude": 0.01184803194297483, "u_time": "MJD", "source": "1", "system": "AB"}, {"time": 58896.374826400075, "band": "i", "instrument": "P48", "telescope": "P48", "magnitude": 17.40002962938992, "e_magnitude": 0.014242693759075182, "u_time": "MJD", "source": "1", "system": "AB"}, {"time": 58898.40578699997, "band": "g", "instrument": "P48", "telescope": "P48", "magnitude": 18.330996842026213, "e_magnitude": 0.019339709117632404, "u_time": "MJD", "source": "1", "system": "AB"}, {"time": 58898.435682899784, "band": "g", "instrument": "P48", "telescope": "P48", "magnitude": 18.3293660866401, "e_magnitude": 0.020574682219943432, "u_time": "MJD", "source": "1", "system": "AB"}, {"time": 58898.43660879973, "band": "g", "instrument": "P48", "telescope": "P48", "magnitude": 18.310231994411794, "e_magnitude": 0.019596644474230134, "u_time": "MJD", "source": "1", "system": "AB"}, {"time": 58898.45672449982, "band": "g", "instrument": "P48", "telescope": "P48", "magnitude": 18.336166744784727, "e_magnitude": 0.019678051081169108, "u_time": "MJD", "source": "1", "system": "AB"}, {"time": 58898.472661999986, "band": "r", "instrument": "P48", "telescope": "P48", "magnitude": 17.595011433870695, "e_magnitude": 0.013511720791678724, "u_time": "MJD", "source": "1", "system": "AB"}, {"time": 58898.47357639996, "band": "r", "instrument": "P48", "telescope": "P48", "magnitude": 17.60773801291196, "e_magnitude": 0.013550487175838758, "u_time": "MJD", "source": "1", "system": "AB"}, {"time": 58898.48773150006, "band": "r", "instrument": "P48", "telescope": "P48", "magnitude": 17.607668624727385, "e_magnitude": 0.013927034433683974, "u_time": "MJD", "source": "1", "system": "AB"}, {"time": 58898.50542820012, "band": "r", "instrument": "P48", "telescope": "P48", "magnitude": 17.616080728866205, "e_magnitude": 0.013935273479725264, "u_time": "MJD", "source": "1", "system": "AB"}, {"time": 58899.39354170021, "band": "g", "instrument": "P48", "telescope": "P48", "magnitude": 18.396928770538608, "e_magnitude": 0.02240617970324083, "u_time": "MJD", "source": "1", "system": "AB"}, {"time": 58899.40422450006, "band": "g", "instrument": "P48", "telescope": "P48", "magnitude": 18.476342163169946, "e_magnitude": 0.023590863454101243, "u_time": "MJD", "source": "1", "system": "AB"}, {"time": 58899.43611110002, "band": "g", "instrument": "P48", "telescope": "P48", "magnitude": 18.45411253885649, "e_magnitude": 0.023678660216162294, "u_time": "MJD", "source": "1", "system": "AB"}, {"time": 58899.454421299975, "band": "r", "instrument": "P48", "telescope": "P48", "magnitude": 17.683710543135597, "e_magnitude": 0.014703259119327086, "u_time": "MJD", "source": "1", "system": "AB"}, {"time": 58899.492928199936, "band": "r", "instrument": "P48", "telescope": "P48", "magnitude": 17.736340397726806, "e_magnitude": 0.01668884634604784, "u_time": "MJD", "source": "1", "system": "AB"}, {"time": 58900.36173610017, "band": "g", "instrument": "P48", "telescope": "P48", "magnitude": 18.577537159326454, "e_magnitude": 0.027540583997340492, "u_time": "MJD", "source": "1", "system": "AB"}, {"time": 58900.393842600286, "band": "g", "instrument": "P48", "telescope": "P48", "magnitude": 18.51037245860153, "e_magnitude": 0.024982114241401534, "u_time": "MJD", "source": "1", "system": "AB"}, {"time": 58900.43314810051, "band": "r", "instrument": "P48", "telescope": "P48", "magnitude": 17.815914414487303, "e_magnitude": 0.01862919214353114, "u_time": "MJD", "source": "1", "system": "AB"}, {"time": 58900.44533560006, "band": "r", "instrument": "P48", "telescope": "P48", "magnitude": 17.689398231300288, "e_magnitude": 0.02350809848892859, "u_time": "MJD", "source": "1", "system": "AB"}, {"time": 58900.527962999884, "band": "g", "instrument": "P48", "telescope": "P48", "magnitude": 18.639625140167496, "e_magnitude": 0.0772435009088175, "u_time": "MJD", "source": "1", "system": "AB"}, {"time": 58901.41461810004, "band": "r", "instrument": "P48", "telescope": "P48", "magnitude": 17.88013997435391, "e_magnitude": 0.017936922597274123, "u_time": "MJD", "source": "1", "system": "AB"}, {"time": 58901.43451389996, "band": "r", "instrument": "P48", "telescope": "P48", "magnitude": 17.87514633068125, "e_magnitude": 0.017156060998548037, "u_time": "MJD", "source": "1", "system": "AB"}, {"time": 58901.45516199991, "band": "r", "instrument": "P48", "telescope": "P48", "magnitude": 17.906341372875918, "e_magnitude": 0.019707640881274427, "u_time": "MJD", "source": "1", "system": "AB"}, {"time": 58901.45607639989, "band": "r", "instrument": "P48", "telescope": "P48", "magnitude": 17.92607871247674, "e_magnitude": 0.021903919567590805, "u_time": "MJD", "source": "1", "system": "AB"}, {"time": 58903.35304399999, "band": "g", "instrument": "P48", "telescope": "P48", "magnitude": 18.898278235019163, "e_magnitude": 0.034222883848605036, "u_time": "MJD", "source": "1", "system": "AB"}, {"time": 58903.359143500216, "band": "g", "instrument": "P48", "telescope": "P48", "magnitude": 18.842361432710685, "e_magnitude": 0.033213908710330524, "u_time": "MJD", "source": "1", "system": "AB"}, {"time": 58903.4129745001, "band": "r", "instrument": "P48", "telescope": "P48", "magnitude": 17.970605840077667, "e_magnitude": 0.017190689933846735, "u_time": "MJD", "source": "1", "system": "AB"}, {"time": 58903.42034720024, "band": "r", "instrument": "P48", "telescope": "P48", "magnitude": 17.985532418645775, "e_magnitude": 0.017703598178902373, "u_time": "MJD", "source": "1", "system": "AB"}, {"time": 58903.45807870012, "band": "r", "instrument": "P48", "telescope": "P48", "magnitude": 17.953427809651302, "e_magnitude": 0.01734444444946924, "u_time": "MJD", "source": "1", "system": "AB"}, {"time": 58903.47219910007, "band": "r", "instrument": "P48", "telescope": "P48", "magnitude": 17.99231665690984, "e_magnitude": 0.019299869948563496, "u_time": "MJD", "source": "1", "system": "AB"}, {"time": 58903.48471060023, "band": "r", "instrument": "P48", "telescope": "P48", "magnitude": 17.999836047492707, "e_magnitude": 0.018145609213278208, "u_time": "MJD", "source": "1", "system": "AB"}, {"time": 58903.504687500186, "band": "r", "instrument": "P48", "telescope": "P48", "magnitude": 17.999297648098796, "e_magnitude": 0.017876921341945764, "u_time": "MJD", "source": "1", "system": "AB"}, {"time": 58904.39664350031, "band": "i", "instrument": "P48", "telescope": "P48", "magnitude": 17.939272041951646, "e_magnitude": 0.019226263856562988, "u_time": "MJD", "source": "1", "system": "AB"}, {"time": 58904.42398149986, "band": "g", "instrument": "P48", "telescope": "P48", "magnitude": 19.107646873123084, "e_magnitude": 0.04689289683204852, "u_time": "MJD", "source": "1", "system": "AB"}, {"time": 58904.42489579972, "band": "g", "instrument": "P48", "telescope": "P48", "magnitude": 18.9575341355571, "e_magnitude": 0.041936350160408385, "u_time": "MJD", "source": "1", "system": "AB"}, {"time": 58904.44518520031, "band": "g", "instrument": "P48", "telescope": "P48", "magnitude": 18.961780343077802, "e_magnitude": 0.041524474164584914, "u_time": "MJD", "source": "1", "system": "AB"}, {"time": 58904.49412039993, "band": "r", "instrument": "P48", "telescope": "P48", "magnitude": 18.039192744820717, "e_magnitude": 0.020856830285962788, "u_time": "MJD", "source": "1", "system": "AB"}, {"time": 58904.495034699794, "band": "r", "instrument": "P48", "telescope": "P48", "magnitude": 18.105813514088506, "e_magnitude": 0.023520110276145437, "u_time": "MJD", "source": "1", "system": "AB"}, {"time": 58904.51445600018, "band": "r", "instrument": "P48", "telescope": "P48", "magnitude": 18.0566588625044, "e_magnitude": 0.02047595954027006, "u_time": "MJD", "source": "1", "system": "AB"}, {"time": 58906.33200229984, "band": "g", "instrument": "P48", "telescope": "P48", "magnitude": 19.158581749682313, "e_magnitude": 0.04939313577905307, "u_time": "MJD", "source": "1", "system": "AB"}, {"time": 58906.33791670017, "band": "g", "instrument": "P48", "telescope": "P48", "magnitude": 19.134870871399468, "e_magnitude": 0.049613001218777555, "u_time": "MJD", "source": "1", "system": "AB"}, {"time": 58906.41437500017, "band": "i", "instrument": "P48", "telescope": "P48", "magnitude": 18.085546106261937, "e_magnitude": 0.017481688924859563, "u_time": "MJD", "source": "1", "system": "AB"}, {"time": 58906.43627310032, "band": "i", "instrument": "P48", "telescope": "P48", "magnitude": 18.03514537967218, "e_magnitude": 0.018868266292389177, "u_time": "MJD", "source": "1", "system": "AB"}, {"time": 58906.45796300005, "band": "r", "instrument": "P48", "telescope": "P48", "magnitude": 18.259356441154466, "e_magnitude": 0.029927244883813976, "u_time": "MJD", "source": "1", "system": "AB"}, {"time": 58906.49703700002, "band": "r", "instrument": "P48", "telescope": "P48", "magnitude": 18.256881217331085, "e_magnitude": 0.03880726726778612, "u_time": "MJD", "source": "1", "system": "AB"}, {"time": 58908.34410879994, "band": "g", "instrument": "P48", "telescope": "P48", "magnitude": 19.226984089557945, "e_magnitude": 0.04510637646603378, "u_time": "MJD", "source": "1", "system": "AB"}, {"time": 58908.350590299815, "band": "g", "instrument": "P48", "telescope": "P48", "magnitude": 19.287083109068682, "e_magnitude": 0.04718345919561824, "u_time": "MJD", "source": "1", "system": "AB"}, {"time": 58908.38177079987, "band": "i", "instrument": "P48", "telescope": "P48", "magnitude": 18.187340726684198, "e_magnitude": 0.01994059911157941, "u_time": "MJD", "source": "1", "system": "AB"}, {"time": 58908.42351850029, "band": "i", "instrument": "P48", "telescope": "P48", "magnitude": 18.15784658609165, "e_magnitude": 0.018294981090799325, "u_time": "MJD", "source": "1", "system": "AB"}, {"time": 58908.440277799964, "band": "r", "instrument": "P48", "telescope": "P48", "magnitude": 18.28860495157732, "e_magnitude": 0.025242692545618336, "u_time": "MJD", "source": "1", "system": "AB"}, {"time": 58908.44119210029, "band": "r", "instrument": "P48", "telescope": "P48", "magnitude": 18.359376450020726, "e_magnitude": 0.02467535352234112, "u_time": "MJD", "source": "1", "system": "AB"}, {"time": 58908.4996181, "band": "r", "instrument": "P48", "telescope": "P48", "magnitude": 18.57051893365423, "e_magnitude": 0.10609844532398165, "u_time": "MJD", "source": "1", "system": "AB"}, {"time": 58911.30961810006, "band": "i", "instrument": "P48", "telescope": "P48", "magnitude": 18.31285158079021, "e_magnitude": 0.03187772776028894, "u_time": "MJD", "source": "1", "system": "AB"}, {"time": 58911.33303239988, "band": "i", "instrument": "P48", "telescope": "P48", "magnitude": 18.363129750389955, "e_magnitude": 0.034630977603311845, "u_time": "MJD", "source": "1", "system": "AB"}, {"time": 58911.4144444, "band": "g", "instrument": "P48", "telescope": "P48", "magnitude": 19.212670024808915, "e_magnitude": 0.05413793767758298, "u_time": "MJD", "source": "1", "system": "AB"}, {"time": 58911.41542820027, "band": "g", "instrument": "P48", "telescope": "P48", "magnitude": 19.34154937274247, "e_magnitude": 0.06273165408505371, "u_time": "MJD", "source": "1", "system": "AB"}, {"time": 58911.464236100204, "band": "r", "instrument": "P48", "telescope": "P48", "magnitude": 18.558218781366406, "e_magnitude": 0.03921916274027496, "u_time": "MJD", "source": "1", "system": "AB"}, {"time": 58911.46516199969, "band": "r", "instrument": "P48", "telescope": "P48", "magnitude": 18.52583393407912, "e_magnitude": 0.03256973809900107, "u_time": "MJD", "source": "1", "system": "AB"}, {"time": 58911.481134299655, "band": "r", "instrument": "P48", "telescope": "P48", "magnitude": 18.61801930664337, "e_magnitude": 0.04056584845368771, "u_time": "MJD", "source": "1", "system": "AB"}, {"time": 58912.36293979967, "band": "i", "instrument": "P48", "telescope": "P48", "magnitude": 18.443542183090713, "e_magnitude": 0.02922586880428982, "u_time": "MJD", "source": "1", "system": "AB"}, {"time": 58912.39667819999, "band": "i", "instrument": "P48", "telescope": "P48", "magnitude": 18.340218148642297, "e_magnitude": 0.02781872304324553, "u_time": "MJD", "source": "1", "system": "AB"}, {"time": 58912.43479170045, "band": "r", "instrument": "P48", "telescope": "P48", "magnitude": 18.601522365423936, "e_magnitude": 0.028639096981890592, "u_time": "MJD", "source": "1", "system": "AB"}, {"time": 58913.29692129977, "band": "g", "instrument": "P48", "telescope": "P48", "magnitude": 19.43238175892157, "e_magnitude": 0.08269463752200565, "u_time": "MJD", "source": "1", "system": "AB"}, {"time": 58913.31840279978, "band": "g", "instrument": "P48", "telescope": "P48", "magnitude": 19.5016706287113, "e_magnitude": 0.09181935201277759, "u_time": "MJD", "source": "1", "system": "AB"}, {"time": 58913.36689810036, "band": "i", "instrument": "P48", "telescope": "P48", "magnitude": 18.432266055120426, "e_magnitude": 0.029000629437261997, "u_time": "MJD", "source": "1", "system": "AB"}, {"time": 58913.395439799875, "band": "i", "instrument": "P48", "telescope": "P48", "magnitude": 18.33256174417002, "e_magnitude": 0.045689965681261796, "u_time": "MJD", "source": "1", "system": "AB"}, {"time": 58913.448634299915, "band": "r", "instrument": "P48", "telescope": "P48", "magnitude": 18.581334803554473, "e_magnitude": 0.03820775273561823, "u_time": "MJD", "source": "1", "system": "AB"}, {"time": 58913.47230320005, "band": "r", "instrument": "P48", "telescope": "P48", "magnitude": 18.607261092043444, "e_magnitude": 0.03926833081740183, "u_time": "MJD", "source": "1", "system": "AB"}, {"time": 58914.27042820025, "band": "i", "instrument": "P48", "telescope": "P48", "magnitude": 18.33645696621322, "e_magnitude": 0.0892723557047328, "u_time": "MJD", "source": "1", "system": "AB"}, {"time": 58914.33215280017, "band": "i", "instrument": "P48", "telescope": "P48", "magnitude": 18.391578218477235, "e_magnitude": 0.03276064293474232, "u_time": "MJD", "source": "1", "system": "AB"}, {"time": 58914.391597200185, "band": "r", "instrument": "P48", "telescope": "P48", "magnitude": 18.57581631854594, "e_magnitude": 0.040930322185626374, "u_time": "MJD", "source": "1", "system": "AB"}, {"time": 58914.40995370038, "band": "r", "instrument": "P48", "telescope": "P48", "magnitude": 18.587509515354732, "e_magnitude": 0.0374295656501896, "u_time": "MJD", "source": "1", "system": "AB"}, {"time": 58914.45446760021, "band": "g", "instrument": "P48", "telescope": "P48", "magnitude": 19.431828017876622, "e_magnitude": 0.08483375222597514, "u_time": "MJD", "source": "1", "system": "AB"}, {"time": 58914.472696799785, "band": "g", "instrument": "P48", "telescope": "P48", "magnitude": 19.511898375654326, "e_magnitude": 0.09285313098731261, "u_time": "MJD", "source": "1", "system": "AB"}, {"time": 58914.510925899725, "band": "r", "instrument": "P48", "telescope": "P48", "magnitude": 18.703984552046563, "e_magnitude": 0.02930282598299154, "u_time": "MJD", "source": "1", "system": "AB"}, {"time": 58915.33114579972, "band": "i", "instrument": "P48", "telescope": "P48", "magnitude": 18.45741042638981, "e_magnitude": 0.03427077330092787, "u_time": "MJD", "source": "1", "system": "AB"}, {"time": 58915.35336809978, "band": "i", "instrument": "P48", "telescope": "P48", "magnitude": 18.511512717253822, "e_magnitude": 0.04100792078156657, "u_time": "MJD", "source": "1", "system": "AB"}, {"time": 58915.42002310045, "band": "r", "instrument": "P48", "telescope": "P48", "magnitude": 18.656750267931358, "e_magnitude": 0.049144764531156813, "u_time": "MJD", "source": "1", "system": "AB"}, {"time": 58915.44996530004, "band": "g", "instrument": "P48", "telescope": "P48", "magnitude": 19.441511592594896, "e_magnitude": 0.1118152525592227, "u_time": "MJD", "source": "1", "system": "AB"}, {"time": 58915.461134299636, "band": "g", "instrument": "P48", "telescope": "P48", "magnitude": 19.487461343649, "e_magnitude": 0.1097313551773225, "u_time": "MJD", "source": "1", "system": "AB"}, {"time": 58936.283738399856, "band": "g", "instrument": "P48", "telescope": "P48", "magnitude": 19.952865355043695, "e_magnitude": 0.08021902172742551, "u_time": "MJD", "source": "1", "system": "AB"}, {"time": 58936.29541670019, "band": "g", "instrument": "P48", "telescope": "P48", "magnitude": 19.77152777151802, "e_magnitude": 0.06833760108823689, "u_time": "MJD", "source": "1", "system": "AB"}, {"time": 58936.30473379977, "band": "g", "instrument": "P48", "telescope": "P48", "magnitude": 19.85532137089299, "e_magnitude": 0.0636418616343293, "u_time": "MJD", "source": "1", "system": "AB"}, {"time": 58936.375393500086, "band": "i", "instrument": "P48", "telescope": "P48", "magnitude": 18.994879821571597, "e_magnitude": 0.03630647741666553, "u_time": "MJD", "source": "1", "system": "AB"}, {"time": 58936.432754599955, "band": "r", "instrument": "P48", "telescope": "P48", "magnitude": 19.266628058463976, "e_magnitude": 0.048294586598004195, "u_time": "MJD", "source": "1", "system": "AB"}, {"time": 58936.45369210001, "band": "r", "instrument": "P48", "telescope": "P48", "magnitude": 19.32167323628748, "e_magnitude": 0.05042963777472158, "u_time": "MJD", "source": "1", "system": "AB"}, {"time": 58936.45511570014, "band": "r", "instrument": "P48", "telescope": "P48", "magnitude": 19.280016889878553, "e_magnitude": 0.05329022923437474, "u_time": "MJD", "source": "1", "system": "AB"}, {"time": 58939.24866899988, "band": "i", "instrument": "P48", "telescope": "P48", "magnitude": 19.188518842841674, "e_magnitude": 0.12055158315891855, "u_time": "MJD", "source": "1", "system": "AB"}, {"time": 58939.269479200244, "band": "i", "instrument": "P48", "telescope": "P48", "magnitude": 19.161675467808656, "e_magnitude": 0.1249072285733312, "u_time": "MJD", "source": "1", "system": "AB"}, {"time": 58939.33291670028, "band": "g", "instrument": "P48", "telescope": "P48", "magnitude": 19.888858925251576, "e_magnitude": 0.11136569115765187, "u_time": "MJD", "source": "1", "system": "AB"}, {"time": 58939.350185200106, "band": "g", "instrument": "P48", "telescope": "P48", "magnitude": 19.811018305202694, "e_magnitude": 0.12719550633822968, "u_time": "MJD", "source": "1", "system": "AB"}, {"time": 58939.351111100055, "band": "g", "instrument": "P48", "telescope": "P48", "magnitude": 19.94789634719877, "e_magnitude": 0.13323936134487935, "u_time": "MJD", "source": "1", "system": "AB"}, {"time": 58939.42185189994, "band": "r", "instrument": "P48", "telescope": "P48", "magnitude": 19.30087919265225, "e_magnitude": 0.13358326230146314, "u_time": "MJD", "source": "1", "system": "AB"}, {"time": 58939.42276620027, "band": "r", "instrument": "P48", "telescope": "P48", "magnitude": 19.163274633870117, "e_magnitude": 0.07894924204545717, "u_time": "MJD", "source": "1", "system": "AB"}, {"time": 58940.317245400045, "band": "i", "instrument": "P48", "telescope": "P48", "magnitude": 19.275376033657764, "e_magnitude": 0.17809415117269733, "u_time": "MJD", "source": "1", "system": "AB"}, {"time": 58940.38421300007, "band": "g", "instrument": "P48", "telescope": "P48", "magnitude": 19.81457044060647, "e_magnitude": 0.10104733519127791, "u_time": "MJD", "source": "1", "system": "AB"}, {"time": 58940.39255789993, "band": "g", "instrument": "P48", "telescope": "P48", "magnitude": 19.967113800890107, "e_magnitude": 0.09201329501398166, "u_time": "MJD", "source": "1", "system": "AB"}, {"time": 58941.280601899605, "band": "i", "instrument": "P48", "telescope": "P48", "magnitude": 19.25890790134142, "e_magnitude": 0.05926156812171275, "u_time": "MJD", "source": "1", "system": "AB"}, {"time": 58941.31133100018, "band": "i", "instrument": "P48", "telescope": "P48", "magnitude": 19.14478508830279, "e_magnitude": 0.04614463367432437, "u_time": "MJD", "source": "1", "system": "AB"}, {"time": 58941.3822337999, "band": "r", "instrument": "P48", "telescope": "P48", "magnitude": 19.4215175305092, "e_magnitude": 0.0758197995282641, "u_time": "MJD", "source": "1", "system": "AB"}, {"time": 58941.40791670047, "band": "r", "instrument": "P48", "telescope": "P48", "magnitude": 19.424311483571095, "e_magnitude": 0.06467705663421515, "u_time": "MJD", "source": "1", "system": "AB"}, {"time": 58941.425046299584, "band": "r", "instrument": "P48", "telescope": "P48", "magnitude": 19.47296978114077, "e_magnitude": 0.06855255895275185, "u_time": "MJD", "source": "1", "system": "AB"}, {"time": 58941.44603010034, "band": "g", "instrument": "P48", "telescope": "P48", "magnitude": 20.07461982084392, "e_magnitude": 0.10861004190395931, "u_time": "MJD", "source": "1", "system": "AB"}, {"time": 58941.4469444002, "band": "g", "instrument": "P48", "telescope": "P48", "magnitude": 20.192817650617265, "e_magnitude": 0.11835833015984684, "u_time": "MJD", "source": "1", "system": "AB"}, {"time": 58941.47621530015, "band": "g", "instrument": "P48", "telescope": "P48", "magnitude": 20.130911895278977, "e_magnitude": 0.10421451981654957, "u_time": "MJD", "source": "1", "system": "AB"}, {"time": 58943.41434030002, "band": "g", "instrument": "P48", "telescope": "P48", "magnitude": 19.927352297259013, "e_magnitude": 0.1464596289074849, "u_time": "MJD", "source": "1", "system": "AB"}, {"time": 58943.415266200434, "band": "g", "instrument": "P48", "telescope": "P48", "magnitude": 19.86519609333379, "e_magnitude": 0.1330462575468641, "u_time": "MJD", "source": "1", "system": "AB"}, {"time": 58944.27369210031, "band": "i", "instrument": "P48", "telescope": "P48", "magnitude": 19.332338753834655, "e_magnitude": 0.10380475320656803, "u_time": "MJD", "source": "1", "system": "AB"}, {"time": 58944.294097200036, "band": "i", "instrument": "P48", "telescope": "P48", "magnitude": 19.144978618559527, "e_magnitude": 0.07162663211042747, "u_time": "MJD", "source": "1", "system": "AB"}, {"time": 58944.39174770005, "band": "r", "instrument": "P48", "telescope": "P48", "magnitude": 19.42513479770501, "e_magnitude": 0.13439563164413912, "u_time": "MJD", "source": "1", "system": "AB"}, {"time": 58944.42054399988, "band": "g", "instrument": "P48", "telescope": "P48", "magnitude": 19.98345671793721, "e_magnitude": 0.23830829589908445, "u_time": "MJD", "source": "1", "system": "AB"}, {"time": 58944.47908560047, "band": "g", "instrument": "P48", "telescope": "P48", "magnitude": 19.971077552448246, "e_magnitude": 0.20943115219158112, "u_time": "MJD", "source": "1", "system": "AB"}, {"time": 58954.26656250004, "band": "r", "instrument": "P48", "telescope": "P48", "magnitude": 19.6337217005878, "e_magnitude": 0.06784158102317087, "u_time": "MJD", "source": "1", "system": "AB"}, {"time": 58954.317893499974, "band": "i", "instrument": "P48", "telescope": "P48", "magnitude": 19.258865464170576, "e_magnitude": 0.07846251242246487, "u_time": "MJD", "source": "1", "system": "AB"}, {"time": 58954.35600689985, "band": "i", "instrument": "P48", "telescope": "P48", "magnitude": 19.447641892712294, "e_magnitude": 0.10009933183370981, "u_time": "MJD", "source": "1", "system": "AB"}, {"time": 58954.383553199936, "band": "g", "instrument": "P48", "telescope": "P48", "magnitude": 20.43143819848345, "e_magnitude": 0.1470377922453511, "u_time": "MJD", "source": "1", "system": "AB"}, {"time": 58954.41615739977, "band": "g", "instrument": "P48", "telescope": "P48", "magnitude": 20.292081958274466, "e_magnitude": 0.17192869124422447, "u_time": "MJD", "source": "1", "system": "AB"}, {"time": 58954.45464120014, "band": "r", "instrument": "P48", "telescope": "P48", "magnitude": 19.610068265069252, "e_magnitude": 0.0984424888271219, "u_time": "MJD", "source": "1", "system": "AB"}, {"time": 58954.47504629986, "band": "r", "instrument": "P48", "telescope": "P48", "magnitude": 19.72747677188618, "e_magnitude": 0.1047761178831201, "u_time": "MJD", "source": "1", "system": "AB"}, {"time": 58955.262280100025, "band": "r", "instrument": "P48", "telescope": "P48", "magnitude": 19.715447478275895, "e_magnitude": 0.06689766362997415, "u_time": "MJD", "source": "1", "system": "AB"}, {"time": 58955.36755790003, "band": "i", "instrument": "P48", "telescope": "P48", "magnitude": 19.61647857947214, "e_magnitude": 0.12500173159743472, "u_time": "MJD", "source": "1", "system": "AB"}, {"time": 58955.377465299796, "band": "i", "instrument": "P48", "telescope": "P48", "magnitude": 19.548429143175134, "e_magnitude": 0.12786246920709524, "u_time": "MJD", "source": "1", "system": "AB"}, {"time": 58955.40245370008, "band": "g", "instrument": "P48", "telescope": "P48", "magnitude": 20.34412706999499, "e_magnitude": 0.12693180786335498, "u_time": "MJD", "source": "1", "system": "AB"}, {"time": 58956.24490739964, "band": "g", "instrument": "P48", "telescope": "P48", "magnitude": 20.211167803562596, "e_magnitude": 0.09653064090938705, "u_time": "MJD", "source": "1", "system": "AB"}, {"time": 58956.30891199969, "band": "r", "instrument": "P48", "telescope": "P48", "magnitude": 19.625566998778467, "e_magnitude": 0.06481489535872119, "u_time": "MJD", "source": "1", "system": "AB"}, {"time": 58962.3422801001, "band": "g", "instrument": "P48", "telescope": "P48", "magnitude": 20.427966350230882, "e_magnitude": 0.12453449168299421, "u_time": "MJD", "source": "1", "system": "AB"}, {"time": 58962.38835649984, "band": "i", "instrument": "P48", "telescope": "P48", "magnitude": 19.645251015508762, "e_magnitude": 0.1262311990300353, "u_time": "MJD", "source": "1", "system": "AB"}, {"time": 58965.25896989973, "band": "g", "instrument": "P48", "telescope": "P48", "magnitude": 20.34777514940634, "e_magnitude": 0.10982047113725861, "u_time": "MJD", "source": "1", "system": "AB"}, {"time": 58965.27293979982, "band": "r", "instrument": "P48", "telescope": "P48", "magnitude": 19.94501360591613, "e_magnitude": 0.10244014883672824, "u_time": "MJD", "source": "1", "system": "AB"}, {"time": 58968.299988399725, "band": "g", "instrument": "P48", "telescope": "P48", "magnitude": 20.49260781778584, "e_magnitude": 0.14331139265092382, "u_time": "MJD", "source": "1", "system": "AB"}, {"time": 58968.369838000275, "band": "r", "instrument": "P48", "telescope": "P48", "magnitude": 19.7471497680209, "e_magnitude": 0.0696253085723642, "u_time": "MJD", "source": "1", "system": "AB"}, {"time": 58974.29508100031, "band": "r", "instrument": "P48", "telescope": "P48", "magnitude": 19.883446276351897, "e_magnitude": 0.16430411801236228, "u_time": "MJD", "source": "1", "system": "AB"}, {"time": 58974.38856479991, "band": "i", "instrument": "P48", "telescope": "P48", "magnitude": 19.496209352427723, "e_magnitude": 0.21435911627873552, "u_time": "MJD", "source": "1", "system": "AB"}, {"time": 58980.2269444, "band": "g", "instrument": "P48", "telescope": "P48", "magnitude": 20.71284784544416, "e_magnitude": 0.11747337776566012, "u_time": "MJD", "source": "1", "system": "AB"}, {"time": 58980.254583299626, "band": "r", "instrument": "P48", "telescope": "P48", "magnitude": 20.119718506805455, "e_magnitude": 0.09430542304087264, "u_time": "MJD", "source": "1", "system": "AB"}, {"time": 58980.3259143997, "band": "r", "instrument": "P48", "telescope": "P48", "magnitude": 20.024360437181468, "e_magnitude": 0.13887754873666142, "u_time": "MJD", "source": "1", "system": "AB"}, {"time": 58991.20945600001, "band": "r", "instrument": "P48", "telescope": "P48", "magnitude": 20.285961316217982, "e_magnitude": 0.12095849954468461, "u_time": "MJD", "source": "1", "system": "AB"}, {"time": 58991.30303239962, "band": "g", "instrument": "P48", "telescope": "P48", "magnitude": 21.093419160015234, "e_magnitude": 0.2397229598463462, "u_time": "MJD", "source": "1", "system": "AB"}, {"time": 58994.25756940013, "band": "g", "instrument": "P48", "telescope": "P48", "magnitude": 20.942866551903315, "e_magnitude": 0.20441992738948983, "u_time": "MJD", "source": "1", "system": "AB"}, {"time": 58994.290439799894, "band": "r", "instrument": "P48", "telescope": "P48", "magnitude": 20.274266492174313, "e_magnitude": 0.09782917072369196, "u_time": "MJD", "source": "1", "system": "AB"}, {"time": 58994.34039349994, "band": "i", "instrument": "P48", "telescope": "P48", "magnitude": 19.915488879249974, "e_magnitude": 0.18270155599239546, "u_time": "MJD", "source": "1", "system": "AB"}, {"time": 58997.21468750015, "band": "g", "instrument": "P48", "telescope": "P48", "magnitude": 20.69641862087169, "e_magnitude": 0.16809241672374292, "u_time": "MJD", "source": "1", "system": "AB"}, {"time": 58997.25584489992, "band": "r", "instrument": "P48", "telescope": "P48", "magnitude": 20.362436024023747, "e_magnitude": 0.12331535726074765, "u_time": "MJD", "source": "1", "system": "AB"}, {"time": 59012.20074070012, "band": "g", "instrument": "P48", "telescope": "P48", "magnitude": 20.733696113279862, "e_magnitude": 0.13420317402267465, "u_time": "MJD", "source": "1", "system": "AB"}, {"time": 59012.2369328998, "band": "r", "instrument": "P48", "telescope": "P48", "magnitude": 20.643319553325277, "e_magnitude": 0.13796000505092762, "u_time": "MJD", "source": "1", "system": "AB"}, {"time": 59018.20835649967, "band": "g", "instrument": "P48", "telescope": "P48", "magnitude": 21.18177961927249, "e_magnitude": 0.2284527026230437, "u_time": "MJD", "source": "1", "system": "AB"}, {"time": 59018.240914399736, "band": "r", "instrument": "P48", "telescope": "P48", "magnitude": 21.105527897988637, "e_magnitude": 0.20954267223726344, "u_time": "MJD", "source": "1", "system": "AB"}, {"time": 59021.24101850018, "band": "r", "instrument": "P48", "telescope": "P48", "magnitude": 21.070545421486752, "e_magnitude": 0.22024597492482498, "u_time": "MJD", "source": "1", "system": "AB"}, {"time": 59039.21464120038, "band": "r", "instrument": "P48", "telescope": "P48", "magnitude": 20.90227691759314, "e_magnitude": 0.18815753240898905, "u_time": "MJD", "source": "1", "system": "AB"}, {"time": 59042.20003469987, "band": "g", "instrument": "P48", "telescope": "P48", "magnitude": 21.229031393608803, "e_magnitude": 0.23650015266192687, "u_time": "MJD", "source": "1", "system": "AB"}, {"time": 58905.415266200434, "band": "i", "instrument": "P48", "telescope": "P48", "magnitude": 18.06202958562777, "e_magnitude": 0.035273199012656874, "u_time": "MJD", "source": "1", "system": "AB"}, {"time": 58909.366041700356, "band": "i", "instrument": "P48", "telescope": "P48", "magnitude": 18.36204475540501, "e_magnitude": 0.054361358697781886, "u_time": "MJD", "source": "1", "system": "AB"}, {"time": 58937.3943403, "band": "g", "instrument": "P48", "telescope": "P48", "magnitude": 19.908576334478006, "e_magnitude": 0.0710345232725638, "u_time": "MJD", "source": "1", "system": "AB"}, {"time": 58953.48026620038, "band": "i", "instrument": "P48", "telescope": "P48", "magnitude": 19.275045440281886, "e_magnitude": 0.10955804437253985, "u_time": "MJD", "source": "1", "system": "AB"}, {"time": 58970.326805599965, "band": "i", "instrument": "P48", "telescope": "P48", "magnitude": 19.622421351226524, "e_magnitude": 0.12198940207480735, "u_time": "MJD", "source": "1", "system": "AB"}, {"time": 58978.32973379968, "band": "i", "instrument": "P48", "telescope": "P48", "magnitude": 19.63629972743534, "e_magnitude": 0.1750142484462755, "u_time": "MJD", "source": "1", "system": "AB"}, {"time": 58985.204074100126, "band": "g", "instrument": "P48", "telescope": "P48", "magnitude": 20.524891977348346, "e_magnitude": 0.11715292748651705, "u_time": "MJD", "source": "1", "system": "AB"}, {"time": 58986.3176851999, "band": "i", "instrument": "P48", "telescope": "P48", "magnitude": 19.974915449647554, "e_magnitude": 0.17526927887429125, "u_time": "MJD", "source": "1", "system": "AB"}, {"time": 58995.16313660005, "band": "g", "instrument": "P48", "telescope": "P48", "magnitude": 20.67144480163995, "e_magnitude": 0.21134328176491007, "u_time": "MJD", "source": "1", "system": "AB"}, {"time": 59015.22258100007, "band": "r", "instrument": "P48", "telescope": "P48", "magnitude": 21.02387498639579, "e_magnitude": 0.23116385576377294, "u_time": "MJD", "source": "1", "system": "AB"}, {"time": 59023.25406249985, "band": "i", "instrument": "P48", "telescope": "P48", "magnitude": 20.269557666286346, "e_magnitude": 0.237903187996621, "u_time": "MJD", "source": "1", "system": "AB"}], "lumdist": [{"value": "8.349400e+01", "u_value": "Mpc", "source": "1"}]}}